data_url/__init__.py
data_url/__main__.py
data_url-1.0.0.dist-info/LICENSE
data_url-1.0.0.dist-info/METADATA
data_url-1.0.0.dist-info/WHEEL
data_url-1.0.0.dist-info/top_level.txt
data_url-1.0.0.dist-info/RECORD
