Metadata-Version: 2.1
Name: data-url
Version: 1.0.0
Summary: UNKNOWN
Home-page: https://github.com/telday/data_url
Author: Ellis Wright
Author-email: ejw393@duck.com
License: UNKNOWN
Project-URL: API Documentation, https://data-url.readthedocs.io/en/latest/#
Platform: UNKNOWN
Classifier: Programming Language :: Python :: 3
Classifier: License :: OSI Approved :: MIT License
Classifier: Operating System :: OS Independent
Requires-Python: >=3.5
License-File: LICENSE
